mcp_server_for_powershell/__init__.py
mcp_server_for_powershell/server.py
mcp_server_for_powershell-1.0.4.dist-info/METADATA
mcp_server_for_powershell-1.0.4.dist-info/WHEEL
mcp_server_for_powershell-1.0.4.dist-info/entry_points.txt
mcp_server_for_powershell-1.0.4.dist-info/licenses/LICENSE
mcp_server_for_powershell-1.0.4.dist-info/RECORD
