Metadata-Version: 2.4
Name: mcp-server-for-powershell
Version: 1.0.4
Summary: MCP Server for PowerShell
Project-URL: Documentation, https://github.com/danielklecha/mcp-server-for-powershell#readme
Project-URL: Issues, https://github.com/danielklecha/mcp-server-for-powershell/issues
Project-URL: Source, https://github.com/danielklecha/mcp-server-for-powershell
Author-email: Daniel Klecha <daniel.klecha@gmail.com>
License-Expression: MIT
License-File: LICENSE
Classifier: Development Status :: 5 - Production/Stable
Classifier: Programming Language :: Python
Classifier: Programming Language :: Python :: 3.10
Classifier: Programming Language :: Python :: 3.11
Classifier: Programming Language :: Python :: 3.12
Classifier: Programming Language :: Python :: 3.13
Classifier: Programming Language :: Python :: 3.14
Classifier: Programming Language :: Python :: Implementation :: CPython
Classifier: Programming Language :: Python :: Implementation :: PyPy
Requires-Python: >=3.10
Requires-Dist: mcp
